<?xml version="1.0" encoding="utf-8"?>
<!DOCTYPE list SYSTEM "spawn.dtd">
<list>
    <spawn spawn_bydefault="true"  name="[rune14_npc1916_01]">
        <npc id="32039" count="1" respawn="60" pos="-11995 -35905 -10856 32496" />	
    </spawn>
    <spawn spawn_bydefault="true"  name="[rune14_npc1916_02]">
        <npc id="32034" count="1" respawn="60" pos="-15928 -36621 -10688 16384" />	
    </spawn>
    <spawn spawn_bydefault="true"  name="[rune14_npc1916_03]">
        <npc id="32035" count="1" respawn="60" pos="-16650 -36889 -10724 49152" />	
    </spawn>
    <spawn spawn_bydefault="true"  name="[rune14_npc1916_04]">
        <npc id="32036" count="1" respawn="60" pos="-15856 -43824 -10688 16384" />	
    </spawn>
    <spawn spawn_bydefault="true"  name="[rune14_npc1916_05]">
        <npc id="32037" count="1" respawn="60" pos="-16625 -44292 -10724 49152" />	
    </spawn>
    <spawn spawn_bydefault="true"  name="[rune14_1916_rb01]">
        <npc id="22142" count="1" respawn="30" respawn_rand="20" pos="-19992 -37953 -10761 0" />	
    </spawn>
    <spawn spawn_bydefault="true"  name="[rune14_1916_01]">
        <territory>	
            <location x="-20536" y="-38219" minz="-10801" maxz="-10501" />
            <location x="-19470" y="-38222" minz="-10801" maxz="-10501" />
            <location x="-19475" y="-37683" minz="-10801" maxz="-10501" />
            <location x="-20538" y="-37691" minz="-10801" maxz="-10501" />
        </territory>
        <npc id="22140" count="2" respawn="60" respawn_rand="20" />	
        <npc id="22141" count="2" respawn="60" respawn_rand="20" />	
        <npc id="22139" count="2" respawn="60" respawn_rand="20" />	
    </spawn>
    <spawn spawn_bydefault="true"  name="[rune14_1916_rb02]">
        <npc id="22143" count="1" respawn="30" respawn_rand="20" pos="-23024 -37952 -10954 0" />	
    </spawn>
    <spawn spawn_bydefault="true"  name="[rune14_1916_02]">
        <territory>	
            <location x="-23568" y="-38236" minz="-10988" maxz="-10738" />
            <location x="-22478" y="-38237" minz="-10988" maxz="-10738" />
            <location x="-22478" y="-37682" minz="-10988" maxz="-10738" />
            <location x="-23573" y="-37679" minz="-10988" maxz="-10738" />
        </territory>
        <npc id="22144" count="2" respawn="60" respawn_rand="20" />	
        <npc id="22145" count="2" respawn="60" respawn_rand="20" />	
        <npc id="22142" count="2" respawn="60" respawn_rand="20" />	
    </spawn>
    <spawn spawn_bydefault="true"  name="[rune14_1916_rb03]">
        <npc id="22142" count="1" respawn="30" respawn_rand="20" pos="-19989 -39813 -10761 0" />	
    </spawn>
    <spawn spawn_bydefault="true"  name="[rune14_1916_03]">
        <territory>	
            <location x="-20537" y="-40099" minz="-10801" maxz="-10451" />
            <location x="-19433" y="-40099" minz="-10801" maxz="-10451" />
            <location x="-19438" y="-39527" minz="-10801" maxz="-10451" />
            <location x="-20541" y="-39528" minz="-10801" maxz="-10451" />
        </territory>
        <npc id="22140" count="2" respawn="60" respawn_rand="20" />	
        <npc id="22141" count="2" respawn="60" respawn_rand="20" />	
        <npc id="22139" count="2" respawn="60" respawn_rand="20" />	
    </spawn>
    <spawn spawn_bydefault="true"  name="[rune14_1916_rb04]">
        <npc id="22143" count="1" respawn="30" respawn_rand="20" pos="-23021 -39822 -10954 0" />	
    </spawn>
    <spawn spawn_bydefault="true"  name="[rune14_1916_04]">
        <territory>	
            <location x="-23571" y="-40101" minz="-10981" maxz="-10731" />
            <location x="-22472" y="-40104" minz="-10981" maxz="-10731" />
            <location x="-22472" y="-39535" minz="-10981" maxz="-10731" />
            <location x="-23565" y="-39535" minz="-10981" maxz="-10731" />
        </territory>
        <npc id="22144" count="2" respawn="60" respawn_rand="20" />	
        <npc id="22145" count="2" respawn="60" respawn_rand="20" />	
        <npc id="22142" count="2" respawn="60" respawn_rand="20" />	
    </spawn>
    <spawn spawn_bydefault="true"  name="[rune14_1916_rb05]">
        <npc id="22142" count="1" respawn="30" respawn_rand="20" pos="-19986 -41702 -10761 0" />	
    </spawn>
    <spawn spawn_bydefault="true"  name="[rune14_1916_05]">
        <territory>	
            <location x="-20533" y="-41978" minz="-10801" maxz="-10451" />
            <location x="-19440" y="-41990" minz="-10801" maxz="-10451" />
            <location x="-19443" y="-41417" minz="-10801" maxz="-10451" />
            <location x="-20535" y="-41411" minz="-10801" maxz="-10451" />
        </territory>
        <npc id="22140" count="2" respawn="60" respawn_rand="20" />	
        <npc id="22141" count="2" respawn="60" respawn_rand="20" />	
        <npc id="22139" count="2" respawn="60" respawn_rand="20" />	
    </spawn>
    <spawn spawn_bydefault="true"  name="[rune14_1916_rb06]">
        <npc id="22143" count="1" respawn="30" respawn_rand="20" pos="-23024 -41693 -10954 0" />	
    </spawn>
    <spawn spawn_bydefault="true"  name="[rune14_1916_06]">
        <territory>	
            <location x="-23571" y="-41977" minz="-10997" maxz="-10747" />
            <location x="-22469" y="-41980" minz="-10997" maxz="-10747" />
            <location x="-22467" y="-41406" minz="-10997" maxz="-10747" />
            <location x="-23571" y="-41420" minz="-10997" maxz="-10747" />
        </territory>
        <npc id="22144" count="2" respawn="60" respawn_rand="20" />	
        <npc id="22145" count="2" respawn="60" respawn_rand="20" />	
        <npc id="22142" count="2" respawn="60" respawn_rand="20" />	
    </spawn>
    <spawn spawn_bydefault="true"  name="[rune14_1916_rb07]">
        <npc id="22142" count="1" respawn="30" respawn_rand="20" pos="-19992 -43562 -10761 0" />	
    </spawn>
    <spawn spawn_bydefault="true"  name="[rune14_1916_07]">
        <territory>	
            <location x="-20532" y="-43837" minz="-10801" maxz="-10451" />
            <location x="-19443" y="-43838" minz="-10801" maxz="-10451" />
            <location x="-19457" y="-43287" minz="-10801" maxz="-10451" />
            <location x="-20536" y="-43287" minz="-10801" maxz="-10451" />
        </territory>
        <npc id="22140" count="2" respawn="60" respawn_rand="20" />	
        <npc id="22141" count="2" respawn="60" respawn_rand="20" />	
        <npc id="22139" count="2" respawn="60" respawn_rand="20" />	
    </spawn>
    <spawn spawn_bydefault="true"  name="[rune14_1916_rb08]">
        <npc id="22143" count="1" respawn="30" respawn_rand="20" pos="-23022 -43556 -10954 0" />	
    </spawn>
    <spawn spawn_bydefault="true"  name="[rune14_1916_08]">
        <territory>	
            <location x="-23567" y="-43834" minz="-10981" maxz="-10731" />
            <location x="-22474" y="-43839" minz="-10981" maxz="-10731" />
            <location x="-22481" y="-43275" minz="-10981" maxz="-10731" />
            <location x="-23570" y="-43273" minz="-10981" maxz="-10731" />
        </territory>
        <npc id="22144" count="2" respawn="60" respawn_rand="20" />	
        <npc id="22145" count="2" respawn="60" respawn_rand="20" />	
        <npc id="22142" count="2" respawn="60" respawn_rand="20" />	
    </spawn>
    <spawn spawn_bydefault="true"  name="[rune14_1916_rb09]">
        <npc id="22142" count="1" respawn="30" respawn_rand="20" pos="-12735 -37938 -10761 0" />	
    </spawn>
    <spawn spawn_bydefault="true"  name="[rune14_1916_09]">
        <territory>	
            <location x="-13280" y="-38221" minz="-10801" maxz="-10451" />
            <location x="-12178" y="-38227" minz="-10801" maxz="-10451" />
            <location x="-12185" y="-37656" minz="-10801" maxz="-10451" />
            <location x="-13287" y="-37659" minz="-10801" maxz="-10451" />
        </territory>
        <npc id="22140" count="2" respawn="60" respawn_rand="20" />	
        <npc id="22141" count="2" respawn="60" respawn_rand="20" />	
        <npc id="22139" count="2" respawn="60" respawn_rand="20" />	
    </spawn>
    <spawn spawn_bydefault="true"  name="[rune14_1916_rb10]">
        <npc id="22143" count="1" respawn="30" respawn_rand="20" pos="-9708 -37943 -10954 0" />	
    </spawn>
    <spawn spawn_bydefault="true"  name="[rune14_1916_10]">
        <territory>	
            <location x="-10239" y="-38207" minz="-10997" maxz="-10647" />
            <location x="-9171" y="-38208" minz="-10997" maxz="-10647" />
            <location x="-9178" y="-37674" minz="-10997" maxz="-10647" />
            <location x="-10241" y="-37673" minz="-10997" maxz="-10647" />
        </territory>
        <npc id="22144" count="2" respawn="60" respawn_rand="20" />	
        <npc id="22145" count="2" respawn="60" respawn_rand="20" />	
        <npc id="22142" count="2" respawn="60" respawn_rand="20" />	
    </spawn>
    <spawn spawn_bydefault="true"  name="[rune14_1916_rb11]">
        <npc id="22142" count="1" respawn="30" respawn_rand="20" pos="-12737 -39810 -10761 0" />	
    </spawn>
    <spawn spawn_bydefault="true"  name="[rune14_1916_11]">
        <territory>	
            <location x="-13283" y="-40090" minz="-10801" maxz="-10451" />
            <location x="-12190" y="-40096" minz="-10801" maxz="-10451" />
            <location x="-12188" y="-39538" minz="-10801" maxz="-10451" />
            <location x="-13287" y="-39536" minz="-10801" maxz="-10451" />
        </territory>
        <npc id="22140" count="2" respawn="60" respawn_rand="20" />	
        <npc id="22141" count="2" respawn="60" respawn_rand="20" />	
        <npc id="22139" count="2" respawn="60" respawn_rand="20" />	
    </spawn>
    <spawn spawn_bydefault="true"  name="[rune14_1916_rb12]">
        <npc id="22143" count="1" respawn="30" respawn_rand="20" pos="-9707 -39820 -10954 0" />	
    </spawn>
    <spawn spawn_bydefault="true"  name="[rune14_1916_12]">
        <territory>	
            <location x="-10209" y="-40060" minz="-10997" maxz="-10647" />
            <location x="-9186" y="-40059" minz="-10997" maxz="-10647" />
            <location x="-9189" y="-39571" minz="-10997" maxz="-10647" />
            <location x="-10212" y="-39573" minz="-10997" maxz="-10647" />
        </territory>
        <npc id="22144" count="2" respawn="60" respawn_rand="20" />	
        <npc id="22145" count="2" respawn="60" respawn_rand="20" />	
        <npc id="22142" count="2" respawn="60" respawn_rand="20" />	
    </spawn>
    <spawn spawn_bydefault="true"  name="[rune14_1916_rb13]">
        <npc id="22142" count="1" respawn="30" respawn_rand="20" pos="-12736 -41694 -10760 0" />	
    </spawn>
    <spawn spawn_bydefault="true"  name="[rune14_1916_13]">
        <territory>	
            <location x="-13283" y="-41969" minz="-10801" maxz="-10451" />
            <location x="-12186" y="-41975" minz="-10801" maxz="-10451" />
            <location x="-12191" y="-41416" minz="-10801" maxz="-10451" />
            <location x="-13279" y="-41413" minz="-10801" maxz="-10451" />
        </territory>
        <npc id="22140" count="2" respawn="60" respawn_rand="20" />	
        <npc id="22141" count="2" respawn="60" respawn_rand="20" />	
        <npc id="22139" count="2" respawn="60" respawn_rand="20" />	
    </spawn>
    <spawn spawn_bydefault="true"  name="[rune14_1916_rb14]">
        <npc id="22143" count="1" respawn="30" respawn_rand="20" pos="-9708 -41687 -10954 0" />	
    </spawn>
    <spawn spawn_bydefault="true"  name="[rune14_1916_14]">
        <territory>	
            <location x="-10222" y="-41941" minz="-10997" maxz="-10647" />
            <location x="-9176" y="-41944" minz="-10997" maxz="-10647" />
            <location x="-9184" y="-41440" minz="-10997" maxz="-10647" />
            <location x="-10226" y="-41441" minz="-10997" maxz="-10647" />
        </territory>
        <npc id="22144" count="2" respawn="60" respawn_rand="20" />	
        <npc id="22145" count="2" respawn="60" respawn_rand="20" />	
        <npc id="22142" count="2" respawn="60" respawn_rand="20" />	
    </spawn>
    <spawn spawn_bydefault="true"  name="[rune14_1916_rb15]">
        <npc id="22142" count="1" respawn="30" respawn_rand="20" pos="-12739 -43552 -10761 0" />	
    </spawn>
    <spawn spawn_bydefault="true"  name="[rune14_1916_15]">
        <territory>	
            <location x="-13271" y="-43814" minz="-10801" maxz="-10451" />
            <location x="-12213" y="-43811" minz="-10801" maxz="-10451" />
            <location x="-12215" y="-43287" minz="-10801" maxz="-10451" />
            <location x="-13273" y="-43285" minz="-10801" maxz="-10451" />
        </territory>
        <npc id="22140" count="2" respawn="60" respawn_rand="20" />	
        <npc id="22141" count="2" respawn="60" respawn_rand="20" />	
        <npc id="22139" count="2" respawn="60" respawn_rand="20" />	
    </spawn>
    <spawn spawn_bydefault="true"  name="[rune14_1916_rb16]">
        <npc id="22143" count="1" respawn="30" respawn_rand="20" pos="-9708 -43545 -10954 0" />	
    </spawn>
    <spawn spawn_bydefault="true"  name="[rune14_1916_16]">
        <territory>	
            <location x="-10244" y="-43813" minz="-10997" maxz="-10697" />
            <location x="-9168" y="-43815" minz="-10997" maxz="-10697" />
            <location x="-9166" y="-43271" minz="-10997" maxz="-10697" />
            <location x="-10249" y="-43270" minz="-10997" maxz="-10697" />
        </territory>
        <npc id="22144" count="2" respawn="60" respawn_rand="20" />	
        <npc id="22145" count="2" respawn="60" respawn_rand="20" />	
        <npc id="22142" count="2" respawn="60" respawn_rand="20" />	
    </spawn>
    <spawn spawn_bydefault="true"  name="[rune14_1916_17]">
        <territory>	
            <location x="-17989" y="-45575" minz="-10784" maxz="-10434" />
            <location x="-17076" y="-45573" minz="-10784" maxz="-10434" />
            <location x="-17077" y="-44557" minz="-10784" maxz="-10434" />
            <location x="-17993" y="-44560" minz="-10784" maxz="-10434" />
        </territory>
        <npc id="22146" count="1" respawn="30" respawn_rand="20" pos="-17436 -45169 -10767 0" />	
        <npc id="22147" count="3" respawn="60" respawn_rand="20" />	
        <npc id="22149" count="2" respawn="60" respawn_rand="20" />	
    </spawn>
    <spawn spawn_bydefault="true"  name="[rune14_1916_17]">
        <territory>	
            <location x="-17989" y="-45575" minz="-10784" maxz="-10434" />
            <location x="-17076" y="-45573" minz="-10784" maxz="-10434" />
            <location x="-17077" y="-44557" minz="-10784" maxz="-10434" />
            <location x="-17993" y="-44560" minz="-10784" maxz="-10434" />
        </territory>
        <npc id="22149" count="2" />	
        <npc id="22150" count="2" />	
    </spawn>
    <spawn spawn_bydefault="true"  name="[rune14_1916_18]">
        <territory>	
            <location x="-19611" y="-45842" minz="-10774" maxz="-10424" />
            <location x="-18561" y="-45843" minz="-10774" maxz="-10424" />
            <location x="-18569" y="-44697" minz="-10774" maxz="-10424" />
            <location x="-19617" y="-44693" minz="-10774" maxz="-10424" />
        </territory>
        <npc id="22146" count="1" respawn="30" respawn_rand="20" pos="-19049 -45334 -10774 0" />	
        <npc id="22142" count="3" respawn="60" respawn_rand="20" />	
        <npc id="22147" count="2" respawn="60" respawn_rand="20" />	
    </spawn>
    <spawn spawn_bydefault="true"  name="[rune14_1916_18]">
        <territory>	
            <location x="-19611" y="-45842" minz="-10774" maxz="-10424" />
            <location x="-18561" y="-45843" minz="-10774" maxz="-10424" />
            <location x="-18569" y="-44697" minz="-10774" maxz="-10424" />
            <location x="-19617" y="-44693" minz="-10774" maxz="-10424" />
        </territory>
        <npc id="22147" count="2" />	
        <npc id="22148" count="2" />	
    </spawn>
    <spawn spawn_bydefault="true"  name="[rune14_1916_19]">
        <territory>	
            <location x="-21009" y="-45601" minz="-10774" maxz="-10424" />
            <location x="-20116" y="-45601" minz="-10774" maxz="-10424" />
            <location x="-20130" y="-44424" minz="-10774" maxz="-10424" />
            <location x="-21020" y="-44421" minz="-10774" maxz="-10424" />
        </territory>
        <npc id="22146" count="1" respawn="30" respawn_rand="20" pos="-20505 -45221 -10774 0" />	
        <npc id="22147" count="3" respawn="60" respawn_rand="20" />	
        <npc id="22150" count="2" respawn="60" respawn_rand="20" />	
    </spawn>
    <spawn spawn_bydefault="true"  name="[rune14_1916_19]">
        <territory>	
            <location x="-21009" y="-45601" minz="-10774" maxz="-10424" />
            <location x="-20116" y="-45601" minz="-10774" maxz="-10424" />
            <location x="-20130" y="-44424" minz="-10774" maxz="-10424" />
            <location x="-21020" y="-44421" minz="-10774" maxz="-10424" />
        </territory>
        <npc id="22148" count="2" />	
        <npc id="22150" count="2" />	
    </spawn>
    <spawn spawn_bydefault="true"  name="[rune14_1916_20]">
        <territory>	
            <location x="-15806" y="-45600" minz="-10767" maxz="-10417" />
            <location x="-14757" y="-45602" minz="-10767" maxz="-10417" />
            <location x="-14754" y="-44346" minz="-10767" maxz="-10417" />
            <location x="-15802" y="-44342" minz="-10767" maxz="-10417" />
        </territory>
        <npc id="22146" count="1" respawn="30" respawn_rand="20" pos="-15242 -45142 -10767 0" />	
        <npc id="22147" count="3" respawn="60" respawn_rand="20" />	
        <npc id="22149" count="2" respawn="60" respawn_rand="20" />	
    </spawn>
    <spawn spawn_bydefault="true"  name="[rune14_1916_20]">
        <territory>	
            <location x="-15806" y="-45600" minz="-10767" maxz="-10417" />
            <location x="-14757" y="-45602" minz="-10767" maxz="-10417" />
            <location x="-14754" y="-44346" minz="-10767" maxz="-10417" />
            <location x="-15802" y="-44342" minz="-10767" maxz="-10417" />
        </territory>
        <npc id="22149" count="2" />	
        <npc id="22150" count="2" />	
    </spawn>
    <spawn spawn_bydefault="true"  name="[rune14_1916_21]">
        <territory>	
            <location x="-14241" y="-45836" minz="-10774" maxz="-10424" />
            <location x="-13191" y="-45838" minz="-10774" maxz="-10424" />
            <location x="-13194" y="-44623" minz="-10774" maxz="-10424" />
            <location x="-14241" y="-44619" minz="-10774" maxz="-10424" />
        </territory>
        <npc id="22146" count="1" respawn="30" respawn_rand="20" pos="-13679 -45329 -10774 0" />	
        <npc id="22142" count="3" respawn="60" respawn_rand="20" />	
        <npc id="22147" count="2" respawn="60" respawn_rand="20" />	
    </spawn>
    <spawn spawn_bydefault="true"  name="[rune14_1916_21]">
        <territory>	
            <location x="-14241" y="-45836" minz="-10774" maxz="-10424" />
            <location x="-13191" y="-45838" minz="-10774" maxz="-10424" />
            <location x="-13194" y="-44623" minz="-10774" maxz="-10424" />
            <location x="-14241" y="-44619" minz="-10774" maxz="-10424" />
        </territory>
        <npc id="22147" count="2" />	
        <npc id="22148" count="2" />	
    </spawn>
    <spawn spawn_bydefault="true"  name="[rune14_1916_22]">
        <territory>	
            <location x="-12641" y="-45667" minz="-10774" maxz="-10424" />
            <location x="-11760" y="-45670" minz="-10774" maxz="-10424" />
            <location x="-11760" y="-44409" minz="-10774" maxz="-10424" />
            <location x="-12639" y="-44404" minz="-10774" maxz="-10424" />
        </territory>
        <npc id="22146" count="1" respawn="30" respawn_rand="20" pos="-12079 -45203 -10774 0" />	
        <npc id="22147" count="3" respawn="60" respawn_rand="20" />	
        <npc id="22150" count="2" respawn="60" respawn_rand="20" />	
    </spawn>
    <spawn spawn_bydefault="true"  name="[rune14_1916_22]">
        <territory>	
            <location x="-12641" y="-45667" minz="-10774" maxz="-10424" />
            <location x="-11760" y="-45670" minz="-10774" maxz="-10424" />
            <location x="-11760" y="-44409" minz="-10774" maxz="-10424" />
            <location x="-12639" y="-44404" minz="-10774" maxz="-10424" />
        </territory>
        <npc id="22148" count="2" />	
        <npc id="22150" count="2" />	
    </spawn>
    <spawn spawn_bydefault="true"  name="[rune14_1916_23]">
        <territory>	
            <location x="-18026" y="-47606" minz="-10878" maxz="-10528" />
            <location x="-16976" y="-47608" minz="-10878" maxz="-10528" />
            <location x="-16976" y="-46386" minz="-10878" maxz="-10528" />
            <location x="-18024" y="-46382" minz="-10878" maxz="-10528" />
        </territory>
        <npc id="22146" count="1" respawn="30" respawn_rand="20" pos="-17464 -47182 -10878 0" />	
        <npc id="22147" count="3" respawn="60" respawn_rand="20" />	
        <npc id="22149" count="2" respawn="60" respawn_rand="20" />	
    </spawn>
    <spawn spawn_bydefault="true"  name="[rune14_1916_23]">
        <territory>	
            <location x="-18026" y="-47606" minz="-10878" maxz="-10528" />
            <location x="-16976" y="-47608" minz="-10878" maxz="-10528" />
            <location x="-16976" y="-46386" minz="-10878" maxz="-10528" />
            <location x="-18024" y="-46382" minz="-10878" maxz="-10528" />
        </territory>
        <npc id="22149" count="2" respawn="60" respawn_rand="20" />	
        <npc id="22150" count="2" respawn="60" respawn_rand="20" />	
    </spawn>
    <spawn spawn_bydefault="true"  name="[rune14_1916_24]">
        <territory>	
            <location x="-19681" y="-47902" minz="-10885" maxz="-10535" />
            <location x="-18631" y="-47904" minz="-10885" maxz="-10535" />
            <location x="-18639" y="-46757" minz="-10885" maxz="-10535" />
            <location x="-19686" y="-46754" minz="-10885" maxz="-10535" />
        </territory>
        <npc id="22146" count="1" respawn="30" respawn_rand="20" pos="-19119 -47395 -10885 0" />	
        <npc id="22142" count="3" respawn="60" respawn_rand="20" />	
        <npc id="22147" count="2" respawn="60" respawn_rand="20" />	
    </spawn>
    <spawn spawn_bydefault="true"  name="[rune14_1916_24]">
        <territory>	
            <location x="-19681" y="-47902" minz="-10885" maxz="-10535" />
            <location x="-18631" y="-47904" minz="-10885" maxz="-10535" />
            <location x="-18639" y="-46757" minz="-10885" maxz="-10535" />
            <location x="-19686" y="-46754" minz="-10885" maxz="-10535" />
        </territory>
        <npc id="22147" count="2" />	
        <npc id="22148" count="2" />	
    </spawn>
    <spawn spawn_bydefault="true"  name="[rune14_1916_25]">
        <territory>	
            <location x="-21009" y="-47637" minz="-10885" maxz="-10535" />
            <location x="-20111" y="-47636" minz="-10885" maxz="-10535" />
            <location x="-20118" y="-46407" minz="-10885" maxz="-10535" />
            <location x="-21014" y="-46405" minz="-10885" maxz="-10535" />
        </territory>
        <npc id="22146" count="1" respawn="30" respawn_rand="20" pos="-20493 -47204 -10885 0" />	
        <npc id="22147" count="3" respawn="60" respawn_rand="20" />	
        <npc id="22150" count="2" respawn="60" respawn_rand="20" />	
    </spawn>
    <spawn spawn_bydefault="true"  name="[rune14_1916_25]">
        <territory>	
            <location x="-21009" y="-47637" minz="-10885" maxz="-10535" />
            <location x="-20111" y="-47636" minz="-10885" maxz="-10535" />
            <location x="-20118" y="-46407" minz="-10885" maxz="-10535" />
            <location x="-21014" y="-46405" minz="-10885" maxz="-10535" />
        </territory>
        <npc id="22148" count="2" />	
        <npc id="22150" count="2" />	
    </spawn>
    <spawn spawn_bydefault="true"  name="[rune14_1916_26]">
        <territory>	
            <location x="-15815" y="-47600" minz="-10875" maxz="-10525" />
            <location x="-14765" y="-47602" minz="-10875" maxz="-10525" />
            <location x="-14762" y="-46346" minz="-10875" maxz="-10525" />
            <location x="-15810" y="-46342" minz="-10875" maxz="-10525" />
        </territory>
        <npc id="22146" count="1" respawn="30" respawn_rand="20" pos="-15250 -47142 -10875 0" />	
        <npc id="22147" count="3" respawn="60" respawn_rand="20" />	
        <npc id="22149" count="2" respawn="60" respawn_rand="20" />	
    </spawn>
    <spawn spawn_bydefault="true"  name="[rune14_1916_26]">
        <territory>	
            <location x="-15815" y="-47600" minz="-10875" maxz="-10525" />
            <location x="-14765" y="-47602" minz="-10875" maxz="-10525" />
            <location x="-14762" y="-46346" minz="-10875" maxz="-10525" />
            <location x="-15810" y="-46342" minz="-10875" maxz="-10525" />
        </territory>
        <npc id="22149" count="2" />	
        <npc id="22150" count="2" />	
    </spawn>
    <spawn spawn_bydefault="true"  name="[rune14_1916_27]">
        <territory>	
            <location x="-14238" y="-47902" minz="-10882" maxz="-10532" />
            <location x="-13188" y="-47904" minz="-10882" maxz="-10532" />
            <location x="-13190" y="-46689" minz="-10882" maxz="-10532" />
            <location x="-14238" y="-46685" minz="-10882" maxz="-10532" />
        </territory>
        <npc id="22146" count="1" respawn="30" respawn_rand="20" pos="-13676 -47395 -10882 0" />	
        <npc id="22142" count="3" respawn="60" respawn_rand="20" />	
        <npc id="22147" count="2" respawn="60" respawn_rand="20" />	
    </spawn>
    <spawn spawn_bydefault="true"  name="[rune14_1916_27]">
        <territory>	
            <location x="-14238" y="-47902" minz="-10882" maxz="-10532" />
            <location x="-13188" y="-47904" minz="-10882" maxz="-10532" />
            <location x="-13190" y="-46689" minz="-10882" maxz="-10532" />
            <location x="-14238" y="-46685" minz="-10882" maxz="-10532" />
        </territory>
        <npc id="22147" count="2" />	
        <npc id="22148" count="2" />	
    </spawn>
    <spawn spawn_bydefault="true"  name="[rune14_1916_28]">
        <territory>	
            <location x="-12649" y="-47667" minz="-10882" maxz="-10532" />
            <location x="-11768" y="-47668" minz="-10882" maxz="-10532" />
            <location x="-11768" y="-46406" minz="-10882" maxz="-10532" />
            <location x="-12647" y="-46404" minz="-10882" maxz="-10532" />
        </territory>
        <npc id="22146" count="1" respawn="30" respawn_rand="20" pos="-12088 -47203 -10882 0" />	
        <npc id="22147" count="3" respawn="60" respawn_rand="20" />	
        <npc id="22150" count="2" respawn="60" respawn_rand="20" />	
    </spawn>
    <spawn spawn_bydefault="true"  name="[rune14_1916_28]">
        <territory>	
            <location x="-12649" y="-47667" minz="-10882" maxz="-10532" />
            <location x="-11768" y="-47668" minz="-10882" maxz="-10532" />
            <location x="-11768" y="-46406" minz="-10882" maxz="-10532" />
            <location x="-12647" y="-46404" minz="-10882" maxz="-10532" />
        </territory>
        <npc id="22148" count="2" />	
        <npc id="22150" count="2" />	
    </spawn>
    <spawn spawn_bydefault="true"  name="[rune14_1916_29]">
        <territory>	
            <location x="-18002" y="-49655" minz="-10961" maxz="-10611" />
            <location x="-17077" y="-49650" minz="-10961" maxz="-10611" />
            <location x="-16953" y="-48434" minz="-10961" maxz="-10611" />
            <location x="-18000" y="-48430" minz="-10961" maxz="-10611" />
        </territory>
        <npc id="22151" count="1" respawn="60" respawn_rand="20" pos="-17440 -49230 -10912 0" />	
        <npc id="22152" count="3" respawn="60" respawn_rand="20" />	
        <npc id="22153" count="2" respawn="60" respawn_rand="20" />	
    </spawn>
    <spawn spawn_bydefault="true"  name="[rune14_1916_29]">
        <territory>	
            <location x="-18002" y="-49655" minz="-10961" maxz="-10611" />
            <location x="-17077" y="-49650" minz="-10961" maxz="-10611" />
            <location x="-16953" y="-48434" minz="-10961" maxz="-10611" />
            <location x="-18000" y="-48430" minz="-10961" maxz="-10611" />
        </territory>
        <npc id="22152" count="4" />	
        <npc id="22150" count="2" />	
    </spawn>
    <spawn spawn_bydefault="true"  name="[rune14_1916_29]">
        <territory>	
            <location x="-18002" y="-49655" minz="-10961" maxz="-10611" />
            <location x="-17077" y="-49650" minz="-10961" maxz="-10611" />
            <location x="-16953" y="-48434" minz="-10961" maxz="-10611" />
            <location x="-18000" y="-48430" minz="-10961" maxz="-10611" />
        </territory>
        <npc id="22154" count="2" respawn="600" respawn_rand="400" />	
    </spawn>
    <spawn spawn_bydefault="true"  name="[rune14_1916_30]">
        <territory>	
            <location x="-19625" y="-49949" minz="-10968" maxz="-10618" />
            <location x="-18576" y="-49951" minz="-10968" maxz="-10618" />
            <location x="-18583" y="-48804" minz="-10968" maxz="-10618" />
            <location x="-19631" y="-48800" minz="-10968" maxz="-10618" />
        </territory>
        <npc id="22151" count="1" respawn="60" respawn_rand="20" pos="-19063 -49441 -10912 0" />	
        <npc id="22152" count="3" respawn="60" respawn_rand="20" />	
        <npc id="22153" count="2" respawn="60" respawn_rand="20" />	
    </spawn>
    <spawn spawn_bydefault="true"  name="[rune14_1916_30]">
        <territory>	
            <location x="-19625" y="-49949" minz="-10968" maxz="-10618" />
            <location x="-18576" y="-49951" minz="-10968" maxz="-10618" />
            <location x="-18583" y="-48804" minz="-10968" maxz="-10618" />
            <location x="-19631" y="-48800" minz="-10968" maxz="-10618" />
        </territory>
        <npc id="22152" count="4" />	
        <npc id="22150" count="2" />	
    </spawn>
    <spawn spawn_bydefault="true"  name="[rune14_1916_30]">
        <territory>	
            <location x="-19625" y="-49949" minz="-10968" maxz="-10618" />
            <location x="-18576" y="-49951" minz="-10968" maxz="-10618" />
            <location x="-18583" y="-48804" minz="-10968" maxz="-10618" />
            <location x="-19631" y="-48800" minz="-10968" maxz="-10618" />
        </territory>
        <npc id="22154" count="2" respawn="600" respawn_rand="400" />	
    </spawn>
    <spawn spawn_bydefault="true"  name="[rune14_1916_31]">
        <territory>	
            <location x="-21002" y="-49661" minz="-10968" maxz="-10618" />
            <location x="-20119" y="-49663" minz="-10968" maxz="-10618" />
            <location x="-20126" y="-48433" minz="-10968" maxz="-10618" />
            <location x="-21008" y="-48429" minz="-10968" maxz="-10618" />
        </territory>
        <npc id="22151" count="1" respawn="60" respawn_rand="20" pos="-20501 -49230 -10912 0" />	
        <npc id="22152" count="3" respawn="60" respawn_rand="20" />	
        <npc id="22153" count="2" respawn="60" respawn_rand="20" />	
    </spawn>
    <spawn spawn_bydefault="true"  name="[rune14_1916_31]">
        <territory>	
            <location x="-21002" y="-49661" minz="-10968" maxz="-10618" />
            <location x="-20119" y="-49663" minz="-10968" maxz="-10618" />
            <location x="-20126" y="-48433" minz="-10968" maxz="-10618" />
            <location x="-21008" y="-48429" minz="-10968" maxz="-10618" />
        </territory>
        <npc id="22152" count="4" />	
        <npc id="22150" count="2" />	
    </spawn>
    <spawn spawn_bydefault="true"  name="[rune14_1916_31]">
        <territory>	
            <location x="-21002" y="-49661" minz="-10968" maxz="-10618" />
            <location x="-20119" y="-49663" minz="-10968" maxz="-10618" />
            <location x="-20126" y="-48433" minz="-10968" maxz="-10618" />
            <location x="-21008" y="-48429" minz="-10968" maxz="-10618" />
        </territory>
        <npc id="22154" count="2" respawn="600" respawn_rand="400" />	
    </spawn>
    <spawn spawn_bydefault="true"  name="[rune14_1916_32]">
        <territory>	
            <location x="-15564" y="-49623" minz="-10958" maxz="-10608" />
            <location x="-14693" y="-49625" minz="-10958" maxz="-10608" />
            <location x="-14690" y="-48369" minz="-10958" maxz="-10608" />
            <location x="-15738" y="-48365" minz="-10958" maxz="-10608" />
        </territory>
        <npc id="22151" count="1" respawn="60" respawn_rand="20" pos="-15178 -49165 -10912 0" />	
        <npc id="22152" count="3" respawn="60" respawn_rand="20" />	
        <npc id="22153" count="2" respawn="60" respawn_rand="20" />	
    </spawn>
    <spawn spawn_bydefault="true"  name="[rune14_1916_32]">
        <territory>	
            <location x="-15564" y="-49623" minz="-10958" maxz="-10608" />
            <location x="-14693" y="-49625" minz="-10958" maxz="-10608" />
            <location x="-14690" y="-48369" minz="-10958" maxz="-10608" />
            <location x="-15738" y="-48365" minz="-10958" maxz="-10608" />
        </territory>
        <npc id="22152" count="4" />	
        <npc id="22150" count="2" />	
    </spawn>
    <spawn spawn_bydefault="true"  name="[rune14_1916_32]">
        <territory>	
            <location x="-15564" y="-49623" minz="-10958" maxz="-10608" />
            <location x="-14693" y="-49625" minz="-10958" maxz="-10608" />
            <location x="-14690" y="-48369" minz="-10958" maxz="-10608" />
            <location x="-15738" y="-48365" minz="-10958" maxz="-10608" />
        </territory>
        <npc id="22154" count="2" respawn="600" respawn_rand="400" />	
    </spawn>
    <spawn spawn_bydefault="true"  name="[rune14_1916_33]">
        <territory>	
            <location x="-14241" y="-49938" minz="-10965" maxz="-10615" />
            <location x="-13192" y="-49940" minz="-10965" maxz="-10615" />
            <location x="-13194" y="-48725" minz="-10965" maxz="-10615" />
            <location x="-14242" y="-48721" minz="-10965" maxz="-10615" />
        </territory>
        <npc id="22151" count="1" respawn="60" respawn_rand="20" pos="-13679 -49431 -10912 0" />	
        <npc id="22152" count="3" respawn="60" respawn_rand="20" />	
        <npc id="22153" count="2" respawn="60" respawn_rand="20" />	
    </spawn>
    <spawn spawn_bydefault="true"  name="[rune14_1916_33]">
        <territory>	
            <location x="-14241" y="-49938" minz="-10965" maxz="-10615" />
            <location x="-13192" y="-49940" minz="-10965" maxz="-10615" />
            <location x="-13194" y="-48725" minz="-10965" maxz="-10615" />
            <location x="-14242" y="-48721" minz="-10965" maxz="-10615" />
        </territory>
        <npc id="22152" count="4" />	
        <npc id="22150" count="2" />	
    </spawn>
    <spawn spawn_bydefault="true"  name="[rune14_1916_33]">
        <territory>	
            <location x="-14241" y="-49938" minz="-10965" maxz="-10615" />
            <location x="-13192" y="-49940" minz="-10965" maxz="-10615" />
            <location x="-13194" y="-48725" minz="-10965" maxz="-10615" />
            <location x="-14242" y="-48721" minz="-10965" maxz="-10615" />
        </territory>
        <npc id="22154" count="2" respawn="600" respawn_rand="400" />	
    </spawn>
    <spawn spawn_bydefault="true"  name="[rune14_1916_34]">
        <territory>	
            <location x="-12651" y="-49690" minz="-10965" maxz="-10615" />
            <location x="-11764" y="-49684" minz="-10965" maxz="-10615" />
            <location x="-11764" y="-48423" minz="-10965" maxz="-10615" />
            <location x="-12649" y="-48427" minz="-10965" maxz="-10615" />
        </territory>
        <npc id="22151" count="1" respawn="60" respawn_rand="20" pos="-12089 -49226 -10912 0" />	
        <npc id="22152" count="3" respawn="60" respawn_rand="20" />	
        <npc id="22153" count="2" respawn="60" respawn_rand="20" />	
    </spawn>
    <spawn spawn_bydefault="true"  name="[rune14_1916_34]">
        <territory>	
            <location x="-12651" y="-49690" minz="-10965" maxz="-10615" />
            <location x="-11764" y="-49684" minz="-10965" maxz="-10615" />
            <location x="-11764" y="-48423" minz="-10965" maxz="-10615" />
            <location x="-12649" y="-48427" minz="-10965" maxz="-10615" />
        </territory>
        <npc id="22152" count="4" />	
        <npc id="22150" count="2" />	
    </spawn>
    <spawn spawn_bydefault="true"  name="[rune14_1916_34]">
        <territory>	
            <location x="-12651" y="-49690" minz="-10965" maxz="-10615" />
            <location x="-11764" y="-49684" minz="-10965" maxz="-10615" />
            <location x="-11764" y="-48423" minz="-10965" maxz="-10615" />
            <location x="-12649" y="-48427" minz="-10965" maxz="-10615" />
        </territory>
        <npc id="22154" count="2" respawn="600" respawn_rand="400" />	
    </spawn>
    <spawn spawn_bydefault="true"  name="[rune14_1916_35]">
        <territory>	
            <location x="-19538" y="-51961" minz="-11075" maxz="-10725" />
            <location x="-18488" y="-51963" minz="-11075" maxz="-10725" />
            <location x="-18496" y="-50817" minz="-11075" maxz="-10725" />
            <location x="-19544" y="-50813" minz="-11075" maxz="-10725" />
        </territory>
        <npc id="22151" count="1" respawn="60" respawn_rand="20" pos="-18976 -51454 -11008 0" />	
        <npc id="22152" count="3" respawn="60" respawn_rand="20" />	
        <npc id="22153" count="2" respawn="60" respawn_rand="20" />	
    </spawn>
    <spawn spawn_bydefault="true"  name="[rune14_1916_35]">
        <territory>	
            <location x="-19538" y="-51961" minz="-11075" maxz="-10725" />
            <location x="-18488" y="-51963" minz="-11075" maxz="-10725" />
            <location x="-18496" y="-50817" minz="-11075" maxz="-10725" />
            <location x="-19544" y="-50813" minz="-11075" maxz="-10725" />
        </territory>
        <npc id="22152" count="4" />	
        <npc id="22150" count="2" />	
    </spawn>
    <spawn spawn_bydefault="true"  name="[rune14_1916_35]">
        <territory>	
            <location x="-19538" y="-51961" minz="-11075" maxz="-10725" />
            <location x="-18488" y="-51963" minz="-11075" maxz="-10725" />
            <location x="-18496" y="-50817" minz="-11075" maxz="-10725" />
            <location x="-19544" y="-50813" minz="-11075" maxz="-10725" />
        </territory>
        <npc id="22154" count="2" respawn="600" respawn_rand="400" />	
    </spawn>
    <spawn spawn_bydefault="true"  name="[rune14_1916_36]">
        <territory>	
            <location x="-21012" y="-51687" minz="-11075" maxz="-10725" />
            <location x="-20106" y="-51687" minz="-11075" maxz="-10725" />
            <location x="-20113" y="-50589" minz="-11075" maxz="-10725" />
            <location x="-21018" y="-50587" minz="-11075" maxz="-10725" />
        </territory>
        <npc id="22151" count="1" respawn="60" respawn_rand="20" pos="-20488 -51386 -11008 0" />	
        <npc id="22152" count="3" respawn="60" respawn_rand="20" />	
        <npc id="22153" count="2" respawn="60" respawn_rand="20" />	
    </spawn>
    <spawn spawn_bydefault="true"  name="[rune14_1916_36]">
        <territory>	
            <location x="-21012" y="-51687" minz="-11075" maxz="-10725" />
            <location x="-20106" y="-51687" minz="-11075" maxz="-10725" />
            <location x="-20113" y="-50589" minz="-11075" maxz="-10725" />
            <location x="-21018" y="-50587" minz="-11075" maxz="-10725" />
        </territory>
        <npc id="22152" count="4" />	
        <npc id="22150" count="2" />	
    </spawn>
    <spawn spawn_bydefault="true"  name="[rune14_1916_36]">
        <territory>	
            <location x="-21012" y="-51687" minz="-11075" maxz="-10725" />
            <location x="-20106" y="-51687" minz="-11075" maxz="-10725" />
            <location x="-20113" y="-50589" minz="-11075" maxz="-10725" />
            <location x="-21018" y="-50587" minz="-11075" maxz="-10725" />
        </territory>
        <npc id="22154" count="2" respawn="600" respawn_rand="400" />	
    </spawn>
    <spawn spawn_bydefault="true"  name="[rune14_1916_37]">
        <territory>	
            <location x="-14303" y="-51996" minz="-11062" maxz="-10712" />
            <location x="-13253" y="-51998" minz="-11062" maxz="-10712" />
            <location x="-13255" y="-50783" minz="-11062" maxz="-10712" />
            <location x="-14303" y="-50779" minz="-11062" maxz="-10712" />
        </territory>
        <npc id="22151" count="1" respawn="60" respawn_rand="20" pos="-13741 -51489 -11008 0" />	
        <npc id="22152" count="3" respawn="60" respawn_rand="20" />	
        <npc id="22153" count="2" respawn="60" respawn_rand="20" />	
    </spawn>
    <spawn spawn_bydefault="true"  name="[rune14_1916_37]">
        <territory>	
            <location x="-14303" y="-51996" minz="-11062" maxz="-10712" />
            <location x="-13253" y="-51998" minz="-11062" maxz="-10712" />
            <location x="-13255" y="-50783" minz="-11062" maxz="-10712" />
            <location x="-14303" y="-50779" minz="-11062" maxz="-10712" />
        </territory>
        <npc id="22152" count="4" />	
        <npc id="22150" count="2" />	
    </spawn>
    <spawn spawn_bydefault="true"  name="[rune14_1916_37]">
        <territory>	
            <location x="-14303" y="-51996" minz="-11062" maxz="-10712" />
            <location x="-13253" y="-51998" minz="-11062" maxz="-10712" />
            <location x="-13255" y="-50783" minz="-11062" maxz="-10712" />
            <location x="-14303" y="-50779" minz="-11062" maxz="-10712" />
        </territory>
        <npc id="22154" count="2" respawn="600" respawn_rand="400" />	
    </spawn>
    <spawn spawn_bydefault="true"  name="[rune14_1916_38]">
        <territory>	
            <location x="-12642" y="-51771" minz="-11064" maxz="-10714" />
            <location x="-11763" y="-51768" minz="-11064" maxz="-10714" />
            <location x="-11763" y="-50507" minz="-11064" maxz="-10714" />
            <location x="-12640" y="-50508" minz="-11064" maxz="-10714" />
        </territory>
        <npc id="22151" count="1" respawn="60" respawn_rand="20" pos="-12080 -51308 -11008 0" />	
        <npc id="22152" count="3" respawn="60" respawn_rand="20" />	
        <npc id="22153" count="2" respawn="60" respawn_rand="20" />	
    </spawn>
    <spawn spawn_bydefault="true"  name="[rune14_1916_38]">
        <territory>	
            <location x="-12642" y="-51771" minz="-11064" maxz="-10714" />
            <location x="-11763" y="-51768" minz="-11064" maxz="-10714" />
            <location x="-11763" y="-50507" minz="-11064" maxz="-10714" />
            <location x="-12640" y="-50508" minz="-11064" maxz="-10714" />
        </territory>
        <npc id="22152" count="4" />	
        <npc id="22150" count="2" />	
    </spawn>
    <spawn spawn_bydefault="true"  name="[rune14_1916_38]">
        <territory>	
            <location x="-12642" y="-51771" minz="-11064" maxz="-10714" />
            <location x="-11763" y="-51768" minz="-11064" maxz="-10714" />
            <location x="-11763" y="-50507" minz="-11064" maxz="-10714" />
            <location x="-12640" y="-50508" minz="-11064" maxz="-10714" />
        </territory>
        <npc id="22154" count="2" respawn="600" respawn_rand="400" />	
    </spawn>
    <spawn spawn_bydefault="true"  name="[rune14_1916_39]">
        <territory>	
            <location x="-20580" y="-52990" minz="-10974" maxz="-10674" />
            <location x="-19621" y="-52991" minz="-10974" maxz="-10674" />
            <location x="-19622" y="-52373" minz="-10974" maxz="-10674" />
            <location x="-20578" y="-52372" minz="-10974" maxz="-10674" />
        </territory>
        <npc id="22155" count="1" respawn="100" respawn_rand="40" />	
        <npc id="22154" count="1" respawn="420" respawn_rand="220" />	
    </spawn>
    <spawn spawn_bydefault="true"  name="[rune14_1916_39]">
        <territory>	
            <location x="-20580" y="-52990" minz="-10974" maxz="-10674" />
            <location x="-19621" y="-52991" minz="-10974" maxz="-10674" />
            <location x="-19622" y="-52373" minz="-10974" maxz="-10674" />
            <location x="-20578" y="-52372" minz="-10974" maxz="-10674" />
        </territory>
        <npc id="22151" count="1" />	
        <npc id="22150" count="2" />	
        <npc id="22147" count="2" />	
    </spawn>
    <spawn spawn_bydefault="true"  name="[rune14_1916_40]">
        <territory>	
            <location x="-20601" y="-54679" minz="-11170" maxz="-10870" />
            <location x="-19642" y="-54680" minz="-11170" maxz="-10870" />
            <location x="-19643" y="-54062" minz="-11170" maxz="-10870" />
            <location x="-20599" y="-54061" minz="-11170" maxz="-10870" />
        </territory>
        <npc id="22155" count="1" respawn="100" respawn_rand="40" />	
        <npc id="22154" count="1" respawn="420" respawn_rand="220" />	
    </spawn>
    <spawn spawn_bydefault="true"  name="[rune14_1916_40]">
        <territory>	
            <location x="-20601" y="-54679" minz="-11170" maxz="-10870" />
            <location x="-19642" y="-54680" minz="-11170" maxz="-10870" />
            <location x="-19643" y="-54062" minz="-11170" maxz="-10870" />
            <location x="-20599" y="-54061" minz="-11170" maxz="-10870" />
        </territory>
        <npc id="22151" count="1" />	
        <npc id="22152" count="2" />	
        <npc id="22153" count="2" />	
    </spawn>
    <spawn spawn_bydefault="true"  name="[rune14_1916_41]">
        <territory>	
            <location x="-13173" y="-52984" minz="-10974" maxz="-10674" />
            <location x="-12214" y="-52985" minz="-10974" maxz="-10674" />
            <location x="-12215" y="-52367" minz="-10974" maxz="-10674" />
            <location x="-13171" y="-52366" minz="-10974" maxz="-10674" />
        </territory>
        <npc id="22155" count="1" respawn="100" respawn_rand="40" />	
        <npc id="22154" count="1" respawn="420" respawn_rand="220" />	
    </spawn>
    <spawn spawn_bydefault="true"  name="[rune14_1916_41]">
        <territory>	
            <location x="-13173" y="-52984" minz="-10974" maxz="-10674" />
            <location x="-12214" y="-52985" minz="-10974" maxz="-10674" />
            <location x="-12215" y="-52367" minz="-10974" maxz="-10674" />
            <location x="-13171" y="-52366" minz="-10974" maxz="-10674" />
        </territory>
        <npc id="22151" count="1" />	
        <npc id="22150" count="2" />	
        <npc id="22147" count="2" />	
    </spawn>
    <spawn spawn_bydefault="true"  name="[rune14_1916_42]">
        <territory>	
            <location x="-13123" y="-54687" minz="-11170" maxz="-10870" />
            <location x="-12164" y="-54688" minz="-11170" maxz="-10870" />
            <location x="-12165" y="-54070" minz="-11170" maxz="-10870" />
            <location x="-13121" y="-54069" minz="-11170" maxz="-10870" />
        </territory>
        <npc id="22155" count="1" respawn="100" respawn_rand="40" />	
        <npc id="22154" count="1" respawn="420" respawn_rand="220" />	
    </spawn>
    <spawn spawn_bydefault="true"  name="[rune14_1916_42]">
        <territory>	
            <location x="-13123" y="-54687" minz="-11170" maxz="-10870" />
            <location x="-12164" y="-54688" minz="-11170" maxz="-10870" />
            <location x="-12165" y="-54070" minz="-11170" maxz="-10870" />
            <location x="-13121" y="-54069" minz="-11170" maxz="-10870" />
        </territory>
        <npc id="22151" count="1" />	
        <npc id="22152" count="2" />	
        <npc id="22153" count="2" />	
    </spawn>
    <spawn spawn_bydefault="true"  name="[rune14_1916_43]">
        <territory>	
            <location x="-17720" y="-54900" minz="-11627" maxz="-11277" />
            <location x="-16402" y="-54902" minz="-11627" maxz="-11277" />
            <location x="-16417" y="-52878" minz="-11627" maxz="-11277" />
            <location x="-18127" y="-52876" minz="-11627" maxz="-11277" />
            <location x="-18136" y="-54120" minz="-11627" maxz="-11277" />
        </territory>
        <npc id="22155" count="2" respawn="90" respawn_rand="40" />	
        <npc id="22159" count="2" respawn="90" respawn_rand="40" />	
        <npc id="22163" count="2" respawn="90" respawn_rand="40" />	
        <npc id="22167" count="1" respawn="90" respawn_rand="40" />	
        <npc id="22171" count="1" respawn="90" respawn_rand="40" />	
    </spawn>
    <spawn spawn_bydefault="true"  name="[rune14_1916_48]">
        <territory>	
            <location x="-18116" y="-57241" minz="-10890" maxz="-10590" />
            <location x="-14637" y="-57250" minz="-10890" maxz="-10590" />
            <location x="-14634" y="-56273" minz="-10890" maxz="-10590" />
            <location x="-18155" y="-56273" minz="-10890" maxz="-10590" />
        </territory>
        <npc id="22167" count="1" respawn="90" respawn_rand="50" pos="-15009 -57012 -10851 0" />	
        <npc id="22171" count="1" respawn="90" respawn_rand="50" pos="-17681 -57028 -10851 0" />	
        <npc id="22155" count="1" respawn="60" respawn_rand="40" />	
        <npc id="22159" count="2" respawn="90" respawn_rand="50" />	
        <npc id="22163" count="2" respawn="90" respawn_rand="50" />	
    </spawn>
    <spawn spawn_bydefault="true"  name="[rune14_1916_75]">
        <territory>	
            <location x="-17768" y="-42146" minz="-10768" maxz="-10418" />
            <location x="-14964" y="-42091" minz="-10768" maxz="-10418" />
            <location x="-14945" y="-39386" minz="-10768" maxz="-10418" />
            <location x="-17734" y="-39403" minz="-10768" maxz="-10418" />
        </territory>
        <npc id="22140" count="3" respawn="1800" respawn_rand="600" />	
        <npc id="22149" count="3" respawn="1800" respawn_rand="600" />	
    </spawn>
    <spawn spawn_bydefault="true"  name="[rune14_1916_51]">
        <territory>	
            <location x="-18857" y="-38081" minz="-10771" maxz="-10421" />
            <location x="-17661" y="-38081" minz="-10771" maxz="-10421" />
            <location x="-17662" y="-37832" minz="-10771" maxz="-10421" />
            <location x="-18856" y="-37831" minz="-10771" maxz="-10421" />
        </territory>
        <npc id="22140" count="3" respawn="800" respawn_rand="200" />	
    </spawn>
    <spawn spawn_bydefault="true"  name="[rune14_1916_62]">
        <territory>	
            <location x="-18817" y="-43681" minz="-10766" maxz="-10466" />
            <location x="-17655" y="-43681" minz="-10766" maxz="-10466" />
            <location x="-17655" y="-43418" minz="-10766" maxz="-10466" />
            <location x="-18817" y="-43419" minz="-10766" maxz="-10466" />
        </territory>
        <npc id="22140" count="3" respawn="800" respawn_rand="200" />	
    </spawn>
    <spawn spawn_bydefault="true"  name="[rune14_1916_63]">
        <territory>	
            <location x="-14976" y="-43684" minz="-10766" maxz="-10466" />
            <location x="-13815" y="-43684" minz="-10766" maxz="-10466" />
            <location x="-13815" y="-43422" minz="-10766" maxz="-10466" />
            <location x="-14976" y="-43422" minz="-10766" maxz="-10466" />
        </territory>
        <npc id="22140" count="3" respawn="800" respawn_rand="200" />	
    </spawn>
    <spawn spawn_bydefault="true"  name="[rune14_1916_64]">
        <territory>	
            <location x="-15013" y="-38073" minz="-10771" maxz="-10421" />
            <location x="-13817" y="-38073" minz="-10771" maxz="-10421" />
            <location x="-13819" y="-37823" minz="-10771" maxz="-10421" />
            <location x="-15013" y="-37822" minz="-10771" maxz="-10421" />
        </territory>
        <npc id="22140" count="3" respawn="800" respawn_rand="200" />	
    </spawn>
    <spawn spawn_bydefault="true"  name="[rune14_1916_52]">
        <npc id="22194" count="1" respawn="90" respawn_rand="40" pos="-21520 -37855 -10804 0" />	
        <npc id="22194" count="1" respawn="90" respawn_rand="40" pos="-21520 -37920 -10804 0" />	
        <npc id="22194" count="1" respawn="90" respawn_rand="40" pos="-21520 -37984 -10804 0" />	
        <npc id="22194" count="1" respawn="90" respawn_rand="40" pos="-21520 -38052 -10804 0" />	
    </spawn>
    <spawn spawn_bydefault="true"  name="[rune14_1916_53]">
        <npc id="22194" count="1" respawn="90" respawn_rand="40" pos="-21520 -39721 -10804 0" />	
        <npc id="22194" count="1" respawn="90" respawn_rand="40" pos="-21520 -39787 -10804 0" />	
        <npc id="22194" count="1" respawn="90" respawn_rand="40" pos="-21520 -39853 -10804 0" />	
        <npc id="22194" count="1" respawn="90" respawn_rand="40" pos="-21520 -39918 -10804 0" />	
    </spawn>
    <spawn spawn_bydefault="true"  name="[rune14_1916_54]">
        <npc id="22194" count="1" respawn="90" respawn_rand="40" pos="-21536 -41590 -10804 0" />	
        <npc id="22194" count="1" respawn="90" respawn_rand="40" pos="-21536 -41656 -10804 0" />	
        <npc id="22194" count="1" respawn="90" respawn_rand="40" pos="-21536 -41720 -10804 0" />	
        <npc id="22194" count="1" respawn="90" respawn_rand="40" pos="-21536 -41783 -10804 0" />	
    </spawn>
    <spawn spawn_bydefault="true"  name="[rune14_1916_55]">
        <npc id="22194" count="1" respawn="90" respawn_rand="40" pos="-21522 -43457 -10804 0" />	
        <npc id="22194" count="1" respawn="90" respawn_rand="40" pos="-21522 -43526 -10804 0" />	
        <npc id="22194" count="1" respawn="90" respawn_rand="40" pos="-21522 -43588 -10804 0" />	
        <npc id="22194" count="1" respawn="90" respawn_rand="40" pos="-21522 -43656 -10804 0" />	
    </spawn>
    <spawn spawn_bydefault="true"  name="[rune14_1916_56]">
        <npc id="22137" count="1" respawn="90" respawn_rand="40" pos="-20495 -42600 -10716 16384" />	
        <npc id="22137" count="1" respawn="90" respawn_rand="40" pos="-20429 -42600 -10716 16384" />	
        <npc id="22137" count="1" respawn="90" respawn_rand="40" pos="-20362 -42599 -10716 16384" />	
        <npc id="22137" count="1" respawn="90" respawn_rand="40" pos="-20297 -42598 -10716 16384" />	
    </spawn>
    <spawn spawn_bydefault="true"  name="[rune14_1916_57]">
        <npc id="22137" count="1" respawn="90" respawn_rand="40" pos="-19681 -40745 -10716 16384" />	
        <npc id="22137" count="1" respawn="90" respawn_rand="40" pos="-19613 -40745 -10716 16384" />	
        <npc id="22137" count="1" respawn="90" respawn_rand="40" pos="-19550 -40744 -10716 16384" />	
        <npc id="22137" count="1" respawn="90" respawn_rand="40" pos="-19486 -40743 -10716 16384" />	
    </spawn>
    <spawn spawn_bydefault="true"  name="[rune14_1916_58]">
        <npc id="22137" count="1" respawn="90" respawn_rand="40" pos="-20494 -38893 -10716 16384" />	
        <npc id="22137" count="1" respawn="90" respawn_rand="40" pos="-20428 -38893 -10716 16384" />	
        <npc id="22137" count="1" respawn="90" respawn_rand="40" pos="-20363 -38892 -10716 16384" />	
        <npc id="22137" count="1" respawn="90" respawn_rand="40" pos="-20296 -38891 -10716 16384" />	
    </spawn>
    <spawn spawn_bydefault="true"  name="[rune14_1916_59]">
        <npc id="22137" count="1" respawn="90" respawn_rand="40" pos="-23231 -38893 -10911 49264" />	
        <npc id="22137" count="1" respawn="90" respawn_rand="40" pos="-23166 -38892 -10911 49264" />	
        <npc id="22137" count="1" respawn="90" respawn_rand="40" pos="-23099 -38891 -10911 49264" />	
        <npc id="22137" count="1" respawn="90" respawn_rand="40" pos="-23031 -38891 -10911 49264" />	
    </spawn>
    <spawn spawn_bydefault="true"  name="[rune14_1916_60]">
        <npc id="22137" count="1" respawn="90" respawn_rand="40" pos="-22519 -40750 -10911 49264" />	
        <npc id="22137" count="1" respawn="90" respawn_rand="40" pos="-22453 -40750 -10911 49264" />	
        <npc id="22137" count="1" respawn="90" respawn_rand="40" pos="-22385 -40749 -10911 49264" />	
        <npc id="22137" count="1" respawn="90" respawn_rand="40" pos="-22320 -40748 -10911 49264" />	
    </spawn>
    <spawn spawn_bydefault="true"  name="[rune14_1916_61]">
        <npc id="22137" count="1" respawn="90" respawn_rand="40" pos="-23228 -42602 -10911 49264" />	
        <npc id="22137" count="1" respawn="90" respawn_rand="40" pos="-23163 -42601 -10911 49264" />	
        <npc id="22137" count="1" respawn="90" respawn_rand="40" pos="-23094 -42600 -10911 49264" />	
        <npc id="22137" count="1" respawn="90" respawn_rand="40" pos="-23027 -42600 -10911 49264" />	
    </spawn>
    <spawn spawn_bydefault="true"  name="[rune14_1916_65]">
        <npc id="22194" count="1" respawn="90" respawn_rand="40" pos="-11196 -37849 -10818 32768" />	
        <npc id="22194" count="1" respawn="90" respawn_rand="40" pos="-11196 -37914 -10818 32768" />	
        <npc id="22194" count="1" respawn="90" respawn_rand="40" pos="-11196 -37981 -10818 32768" />	
        <npc id="22194" count="1" respawn="90" respawn_rand="40" pos="-11196 -38048 -10818 32768" />	
    </spawn>
    <spawn spawn_bydefault="true"  name="[rune14_1916_66]">
        <npc id="22194" count="1" respawn="90" respawn_rand="40" pos="-11195 -39717 -10818 32768" />	
        <npc id="22194" count="1" respawn="90" respawn_rand="40" pos="-11195 -39783 -10818 32768" />	
        <npc id="22194" count="1" respawn="90" respawn_rand="40" pos="-11195 -39847 -10818 32768" />	
        <npc id="22194" count="1" respawn="90" respawn_rand="40" pos="-11195 -39917 -10818 32768" />	
    </spawn>
    <spawn spawn_bydefault="true"  name="[rune14_1916_67]">
        <npc id="22194" count="1" respawn="90" respawn_rand="40" pos="-11197 -41589 -10818 32768" />	
        <npc id="22194" count="1" respawn="90" respawn_rand="40" pos="-11197 -41654 -10818 32768" />	
        <npc id="22194" count="1" respawn="90" respawn_rand="40" pos="-11197 -41720 -10818 32768" />	
        <npc id="22194" count="1" respawn="90" respawn_rand="40" pos="-11197 -41786 -10818 32768" />	
    </spawn>
    <spawn spawn_bydefault="true"  name="[rune14_1916_68]">
        <npc id="22194" count="1" respawn="90" respawn_rand="40" pos="-11200 -43454 -10818 32768" />	
        <npc id="22194" count="1" respawn="90" respawn_rand="40" pos="-11200 -43520 -10818 32768" />	
        <npc id="22194" count="1" respawn="90" respawn_rand="40" pos="-11200 -43587 -10818 32768" />	
        <npc id="22194" count="1" respawn="90" respawn_rand="40" pos="-11200 -43652 -10818 32768" />	
    </spawn>
    <spawn spawn_bydefault="true"  name="[rune14_1916_69]">
        <npc id="22137" count="1" respawn="90" respawn_rand="40" pos="-12441 -42594 -10716 16384" />	
        <npc id="22137" count="1" respawn="90" respawn_rand="40" pos="-12376 -42593 -10716 16384" />	
        <npc id="22137" count="1" respawn="90" respawn_rand="40" pos="-12311 -42593 -10716 16384" />	
        <npc id="22137" count="1" respawn="90" respawn_rand="40" pos="-12248 -42592 -10716 16384" />	
    </spawn>
    <spawn spawn_bydefault="true"  name="[rune14_1916_70]">
        <npc id="22137" count="1" respawn="90" respawn_rand="40" pos="-9693 -42612 -10909 49264" />	
        <npc id="22137" count="1" respawn="90" respawn_rand="40" pos="-9626 -42611 -10909 49264" />	
        <npc id="22137" count="1" respawn="90" respawn_rand="40" pos="-9559 -42610 -10909 49264" />	
        <npc id="22137" count="1" respawn="90" respawn_rand="40" pos="-9495 -42610 -10909 49264" />	
    </spawn>
    <spawn spawn_bydefault="true"  name="[rune14_1916_71]">
        <npc id="22137" count="1" respawn="90" respawn_rand="40" pos="-13241 -40727 -10716 16384" />	
        <npc id="22137" count="1" respawn="90" respawn_rand="40" pos="-13174 -40727 -10716 16384" />	
        <npc id="22137" count="1" respawn="90" respawn_rand="40" pos="-13106 -40726 -10716 16384" />	
        <npc id="22137" count="1" respawn="90" respawn_rand="40" pos="-13041 -40726 -10716 16384" />	
    </spawn>
    <spawn spawn_bydefault="true"  name="[rune14_1916_72]">
        <npc id="22137" count="1" respawn="90" respawn_rand="40" pos="-10409 -40756 -10909 49264" />	
        <npc id="22137" count="1" respawn="90" respawn_rand="40" pos="-10344 -40755 -10909 49264" />	
        <npc id="22137" count="1" respawn="90" respawn_rand="40" pos="-10279 -40754 -10909 49264" />	
        <npc id="22137" count="1" respawn="90" respawn_rand="40" pos="-10213 -40754 -10909 49264" />	
    </spawn>
    <spawn spawn_bydefault="true"  name="[rune14_1916_73]">
        <npc id="22137" count="1" respawn="90" respawn_rand="40" pos="-12429 -38897 -10716 16384" />	
        <npc id="22137" count="1" respawn="90" respawn_rand="40" pos="-12363 -38896 -10716 16384" />	
        <npc id="22137" count="1" respawn="90" respawn_rand="40" pos="-12296 -38895 -10716 16384" />	
        <npc id="22137" count="1" respawn="90" respawn_rand="40" pos="-12230 -38895 -10716 16384" />	
    </spawn>
    <spawn spawn_bydefault="true"  name="[rune14_1916_74]">
        <npc id="22137" count="1" respawn="90" respawn_rand="40" pos="-9689 -38907 -10909 49264" />	
        <npc id="22137" count="1" respawn="90" respawn_rand="40" pos="-9624 -38907 -10909 49264" />	
        <npc id="22137" count="1" respawn="90" respawn_rand="40" pos="-9558 -38906 -10909 49264" />	
        <npc id="22137" count="1" respawn="90" respawn_rand="40" pos="-9491 -38905 -10909 49264" />	
    </spawn>
    <spawn spawn_bydefault="true"  name="[rune14_1916_77]">
        <npc id="22138" count="1" respawn="90" respawn_rand="40" pos="-19888 -45547 -10720 32768" />	
        <npc id="22138" count="1" respawn="90" respawn_rand="40" pos="-19888 -45619 -10720 32768" />	
        <npc id="22138" count="1" respawn="90" respawn_rand="40" pos="-19888 -45691 -10720 32768" />	
        <npc id="22138" count="1" respawn="90" respawn_rand="40" pos="-18324 -44438 -10720 32768" />	
        <npc id="22138" count="1" respawn="90" respawn_rand="40" pos="-18324 -44582 -10720 32768" />	
        <npc id="22138" count="1" respawn="90" respawn_rand="40" pos="-18324 -44516 -10720 32768" />	
        <npc id="22138" count="1" respawn="90" respawn_rand="40" pos="-14477 -44437 -10720 0" />	
        <npc id="22138" count="1" respawn="90" respawn_rand="40" pos="-14477 -44511 -10720 0" />	
        <npc id="22138" count="1" respawn="90" respawn_rand="40" pos="-14477 -44582 -10720 0" />	
        <npc id="22138" count="1" respawn="90" respawn_rand="40" pos="-12929 -45549 -10720 0" />	
        <npc id="22138" count="1" respawn="90" respawn_rand="40" pos="-12930 -45619 -10720 0" />	
        <npc id="22138" count="1" respawn="90" respawn_rand="40" pos="-12929 -45688 -10720 0" />	
        <npc id="22138" count="1" respawn="90" respawn_rand="40" pos="-19884 -47598 -10816 32768" />	
        <npc id="22138" count="1" respawn="90" respawn_rand="40" pos="-19885 -47667 -10816 32768" />	
        <npc id="22138" count="1" respawn="90" respawn_rand="40" pos="-19883 -47740 -10816 32768" />	
        <npc id="22138" count="1" respawn="90" respawn_rand="40" pos="-18329 -46501 -10816 32768" />	
        <npc id="22138" count="1" respawn="90" respawn_rand="40" pos="-18330 -46571 -10816 32768" />	
        <npc id="22138" count="1" respawn="90" respawn_rand="40" pos="-18329 -46643 -10816 32768" />	
        <npc id="22138" count="1" respawn="90" respawn_rand="40" pos="-14479 -46506 -10816 0" />	
        <npc id="22138" count="1" respawn="90" respawn_rand="40" pos="-14480 -46576 -10816 0" />	
        <npc id="22138" count="1" respawn="90" respawn_rand="40" pos="-14479 -46643 -10816 0" />	
        <npc id="22138" count="1" respawn="90" respawn_rand="40" pos="-12925 -47599 -10816 0" />	
        <npc id="22138" count="1" respawn="90" respawn_rand="40" pos="-12925 -47669 -10816 0" />	
        <npc id="22138" count="1" respawn="90" respawn_rand="40" pos="-12925 -47740 -10816 0" />	
        <npc id="22138" count="1" respawn="90" respawn_rand="40" pos="-19883 -49658 -10912 32768" />	
        <npc id="22138" count="1" respawn="90" respawn_rand="40" pos="-19884 -49719 -10912 32768" />	
        <npc id="22138" count="1" respawn="90" respawn_rand="40" pos="-19883 -49780 -10912 32768" />	
        <npc id="22138" count="1" respawn="90" respawn_rand="40" pos="-18340 -48560 -10912 32768" />	
        <npc id="22138" count="1" respawn="90" respawn_rand="40" pos="-18341 -48623 -10912 32768" />	
        <npc id="22138" count="1" respawn="90" respawn_rand="40" pos="-18340 -48684 -10912 32768" />	
        <npc id="22138" count="1" respawn="90" respawn_rand="40" pos="-14483 -48552 -10912 0" />	
        <npc id="22138" count="1" respawn="90" respawn_rand="40" pos="-14484 -48620 -10912 0" />	
        <npc id="22138" count="1" respawn="90" respawn_rand="40" pos="-14483 -48693 -10912 0" />	
        <npc id="22138" count="1" respawn="90" respawn_rand="40" pos="-12922 -49647 -10912 0" />	
        <npc id="22138" count="1" respawn="90" respawn_rand="40" pos="-12922 -49720 -10912 0" />	
        <npc id="22138" count="1" respawn="90" respawn_rand="40" pos="-12922 -49787 -10912 0" />	
        <npc id="22138" count="1" respawn="90" respawn_rand="40" pos="-19893 -51687 -11008 32768" />	
        <npc id="22138" count="1" respawn="90" respawn_rand="40" pos="-19894 -51759 -11008 32768" />	
        <npc id="22138" count="1" respawn="90" respawn_rand="40" pos="-19893 -51831 -11008 32768" />	
        <npc id="22138" count="1" respawn="90" respawn_rand="40" pos="-12928 -51686 -11008 0" />	
        <npc id="22138" count="1" respawn="90" respawn_rand="40" pos="-12928 -51758 -11008 0" />	
        <npc id="22138" count="1" respawn="90" respawn_rand="40" pos="-12928 -51830 -11008 0" />	
        <npc id="22138" count="1" respawn="90" respawn_rand="40" pos="-16814 -45742 -10720 0" />	
        <npc id="22138" count="1" respawn="90" respawn_rand="40" pos="-16814 -45827 -10720 0" />	
        <npc id="22138" count="1" respawn="90" respawn_rand="40" pos="-16814 -45910 -10720 0" />	
        <npc id="22138" count="1" respawn="90" respawn_rand="40" pos="-16814 -45993 -10720 0" />	
        <npc id="22138" count="1" respawn="90" respawn_rand="40" pos="-15936 -45732 -10720 32768" />	
        <npc id="22138" count="1" respawn="90" respawn_rand="40" pos="-15936 -45813 -10720 32768" />	
        <npc id="22138" count="1" respawn="90" respawn_rand="40" pos="-15936 -45896 -10720 32768" />	
        <npc id="22138" count="1" respawn="90" respawn_rand="40" pos="-15936 -45976 -10720 32768" />	
        <npc id="22138" count="1" respawn="90" respawn_rand="40" pos="-16805 -47800 -10816 0" />	
        <npc id="22138" count="1" respawn="90" respawn_rand="40" pos="-16805 -47879 -10816 0" />	
        <npc id="22138" count="1" respawn="90" respawn_rand="40" pos="-16805 -47957 -10816 0" />	
        <npc id="22138" count="1" respawn="90" respawn_rand="40" pos="-16805 -48037 -10816 0" />	
        <npc id="22138" count="1" respawn="90" respawn_rand="40" pos="-15935 -47790 -10816 32768" />	
        <npc id="22138" count="1" respawn="90" respawn_rand="40" pos="-15936 -47868 -10816 32768" />	
        <npc id="22138" count="1" respawn="90" respawn_rand="40" pos="-15935 -47949 -10816 32768" />	
        <npc id="22138" count="1" respawn="90" respawn_rand="40" pos="-15935 -48028 -10816 32768" />	
        <npc id="22138" count="1" respawn="90" respawn_rand="40" pos="-16859 -49890 -10912 0" />	
        <npc id="22138" count="1" respawn="90" respawn_rand="40" pos="-16896 -49967 -10912 0" />	
        <npc id="22138" count="1" respawn="90" respawn_rand="40" pos="-16927 -50045 -10912 0" />	
        <npc id="22138" count="1" respawn="90" respawn_rand="40" pos="-16952 -50127 -10912 0" />	
        <npc id="22138" count="1" respawn="90" respawn_rand="40" pos="-15899 -49871 -10912 32768" />	
        <npc id="22138" count="1" respawn="90" respawn_rand="40" pos="-15870 -49949 -10912 32768" />	
        <npc id="22138" count="1" respawn="90" respawn_rand="40" pos="-15842 -50026 -10912 32768" />	
        <npc id="22138" count="1" respawn="90" respawn_rand="40" pos="-15812 -50107 -10912 32768" />	
        <npc id="22138" count="1" respawn="90" respawn_rand="40" pos="-18325 -50610 -11008 0" />	
        <npc id="22138" count="1" respawn="90" respawn_rand="40" pos="-18326 -50684 -11008 0" />	
        <npc id="22138" count="1" respawn="90" respawn_rand="40" pos="-18325 -50757 -11008 0" />	
        <npc id="22138" count="1" respawn="90" respawn_rand="40" pos="-14466 -50612 -11008 32768" />	
        <npc id="22138" count="1" respawn="90" respawn_rand="40" pos="-14466 -50684 -11008 32768" />	
        <npc id="22138" count="1" respawn="90" respawn_rand="40" pos="-14466 -50759 -11008 32768" />	
    </spawn>
    <spawn spawn_bydefault="true"  name="[rune14_mb1916_02]">
        <npc id="32068" count="1" respawn="90" pos="-16395 -54055 -10439 15992" />	
    </spawn>
    <spawn spawn_bydefault="true"  name="[rune14_mb1916_03]">
        <npc id="32051" count="1" respawn="90" pos="-17248 -54832 -10424 16384" />	
        <npc id="32051" count="1" respawn="90" pos="-15547 -54835 -10424 16384" />	
        <npc id="32051" count="1" respawn="90" pos="-18116 -54831 -10579 16384" />	
        <npc id="32051" count="1" respawn="90" pos="-14645 -54836 -10577 16384" />	
    </spawn>
    <spawn spawn_bydefault="true"  name="[rune14_mb1916_03]" event_name="[guard_of_andreas]">
        <npc id="32038" count="1" respawn="90" pos="-16384 -53197 -10439 15992" />
        <npc id="22175" count="1" respawn="90" pos="-18008 -53394 -10594 16384" />	
        <npc id="22175" count="1" respawn="90" pos="-17653 -53399 -10594 16384" />	
        <npc id="22175" count="1" respawn="90" pos="-17827 -53575 -10594 16384" />	
        <npc id="22175" count="1" respawn="90" pos="-18008 -53749 -10594 16384" />	
        <npc id="22175" count="1" respawn="90" pos="-17653 -53754 -10594 16384" />	
        <npc id="22175" count="1" respawn="90" pos="-17827 -53930 -10594 16384" />	
        <npc id="22175" count="1" respawn="90" pos="-18008 -54100 -10594 16384" />	
        <npc id="22175" count="1" respawn="90" pos="-17653 -54105 -10594 16384" />	
        <npc id="22175" count="1" respawn="90" pos="-17275 -52577 -10594 16384" />	
        <npc id="22175" count="1" respawn="90" pos="-16917 -52577 -10594 16384" />	
        <npc id="22175" count="1" respawn="90" pos="-16738 -52577 -10594 16384" />	
        <npc id="22175" count="1" respawn="90" pos="-17003 -52404 -10594 16384" />	
        <npc id="22175" count="1" respawn="90" pos="-17353 -52404 -10594 16384" />	
        <npc id="22175" count="1" respawn="90" pos="-17362 -52752 -10594 16384" />	
        <npc id="22175" count="1" respawn="90" pos="-17006 -52752 -10594 16384" />	
        <npc id="22175" count="1" respawn="90" pos="-17721 -52752 -10594 16384" />	
        <npc id="22175" count="1" respawn="90" pos="-17648 -52968 -10594 16384" />	
        <npc id="22175" count="1" respawn="90" pos="-17292 -52968 -10594 16384" />	
        <npc id="22175" count="1" respawn="90" pos="-16374 -52577 -10594 16384" />	
        <npc id="22175" count="1" respawn="90" pos="-16648 -52404 -10594 16384" />	
        <npc id="22175" count="1" respawn="90" pos="-16284 -52404 -10594 16384" />	
        <npc id="22175" count="1" respawn="90" pos="-16013 -52577 -10594 16384" />	
        <npc id="22175" count="1" respawn="90" pos="-15658 -52577 -10594 16384" />	
        <npc id="22175" count="1" respawn="90" pos="-15306 -52577 -10594 16384" />	
        <npc id="22175" count="1" respawn="90" pos="-15923 -52404 -10594 16384" />	
        <npc id="22175" count="1" respawn="90" pos="-15568 -52404 -10594 16384" />	
        <npc id="22175" count="1" respawn="90" pos="-15216 -52404 -10594 16384" />	
        <npc id="22175" count="1" respawn="90" pos="-15745 -52752 -10594 16384" />	
        <npc id="22175" count="1" respawn="90" pos="-15394 -52752 -10594 16384" />	
        <npc id="22175" count="1" respawn="90" pos="-15475 -52969 -10594 16384" />	
        <npc id="22175" count="1" respawn="90" pos="-15119 -52969 -10594 16384" />	
        <npc id="22175" count="1" respawn="90" pos="-15149 -53411 -10594 16384" />	
        <npc id="22175" count="1" respawn="90" pos="-14794 -53416 -10594 16384" />	
        <npc id="22175" count="1" respawn="90" pos="-14968 -53592 -10594 16384" />	
        <npc id="22175" count="1" respawn="90" pos="-15149 -53766 -10594 16384" />	
        <npc id="22175" count="1" respawn="90" pos="-14794 -53771 -10594 16384" />	
        <npc id="22175" count="1" respawn="90" pos="-14968 -53947 -10594 16384" />	
        <npc id="22175" count="1" respawn="90" pos="-15149 -54117 -10594 16384" />	
        <npc id="22175" count="1" respawn="90" pos="-14794 -54122 -10594 16384" />	
        <npc id="22176" count="1" respawn="90" pos="-16380 -45796 -10726 16384" />	
        <npc id="22176" count="1" respawn="90" pos="-16290 -45796 -10726 16384" />	
        <npc id="22176" count="1" respawn="90" pos="-16471 -45796 -10726 16384" />	
        <npc id="22176" count="1" respawn="90" pos="-16380 -45514 -10726 16384" />	
        <npc id="22176" count="1" respawn="90" pos="-16290 -45514 -10726 16384" />	
        <npc id="22176" count="1" respawn="90" pos="-16471 -45514 -10726 16384" />	
        <npc id="22176" count="1" respawn="90" pos="-16380 -45243 -10726 16384" />	
        <npc id="22176" count="1" respawn="90" pos="-16290 -45243 -10726 16384" />	
        <npc id="22176" count="1" respawn="90" pos="-16471 -45243 -10726 16384" />	
        <npc id="22176" count="1" respawn="90" pos="-16380 -44973 -10726 16384" />	
        <npc id="22176" count="1" respawn="90" pos="-16290 -44973 -10726 16384" />	
        <npc id="22176" count="1" respawn="90" pos="-16471 -44973 -10726 16384" />	
        <npc id="22176" count="1" respawn="90" pos="-16380 -44703 -10726 16384" />	
        <npc id="22176" count="1" respawn="90" pos="-16290 -44703 -10726 16384" />	
        <npc id="22176" count="1" respawn="90" pos="-16471 -44703 -10726 16384" />	
        <npc id="22176" count="1" respawn="90" pos="-16382 -47685 -10822 16384" />	
        <npc id="22176" count="1" respawn="90" pos="-16292 -47685 -10822 16384" />	
        <npc id="22176" count="1" respawn="90" pos="-16474 -47685 -10822 16384" />	
        <npc id="22176" count="1" respawn="90" pos="-16382 -47404 -10822 16384" />	
        <npc id="22176" count="1" respawn="90" pos="-16292 -47404 -10822 16384" />	
        <npc id="22176" count="1" respawn="90" pos="-16474 -47404 -10822 16384" />	
        <npc id="22176" count="1" respawn="90" pos="-16382 -47133 -10822 16384" />	
        <npc id="22176" count="1" respawn="90" pos="-16292 -47133 -10822 16384" />	
        <npc id="22176" count="1" respawn="90" pos="-16474 -47133 -10822 16384" />	
        <npc id="22176" count="1" respawn="90" pos="-16382 -46862 -10822 16384" />	
        <npc id="22176" count="1" respawn="90" pos="-16292 -46862 -10822 16384" />	
        <npc id="22176" count="1" respawn="90" pos="-16474 -46862 -10822 16384" />	
        <npc id="22176" count="1" respawn="90" pos="-16382 -46593 -10822 16384" />	
        <npc id="22176" count="1" respawn="90" pos="-16292 -46593 -10822 16384" />	
        <npc id="22176" count="1" respawn="90" pos="-16474 -46593 -10822 16384" />	
        <npc id="22176" count="1" respawn="90" pos="-16382 -46333 -10822 16384" />	
        <npc id="22176" count="1" respawn="90" pos="-16292 -46333 -10822 16384" />	
        <npc id="22176" count="1" respawn="90" pos="-16474 -46333 -10822 16384" />	
        <npc id="22176" count="1" respawn="90" pos="-16381 -49743 -10918 16384" />	
        <npc id="22176" count="1" respawn="90" pos="-16291 -49743 -10918 16384" />	
        <npc id="22176" count="1" respawn="90" pos="-16473 -49743 -10918 16384" />	
        <npc id="22176" count="1" respawn="90" pos="-16381 -49461 -10918 16384" />	
        <npc id="22176" count="1" respawn="90" pos="-16291 -49461 -10918 16384" />	
        <npc id="22176" count="1" respawn="90" pos="-16473 -49461 -10918 16384" />	
        <npc id="22176" count="1" respawn="90" pos="-16381 -49191 -10918 16384" />	
        <npc id="22176" count="1" respawn="90" pos="-16291 -49191 -10918 16384" />	
        <npc id="22176" count="1" respawn="90" pos="-16473 -49191 -10918 16384" />	
        <npc id="22176" count="1" respawn="90" pos="-16381 -48920 -10918 16384" />	
        <npc id="22176" count="1" respawn="90" pos="-16291 -48920 -10918 16384" />	
        <npc id="22176" count="1" respawn="90" pos="-16473 -48920 -10918 16384" />	
        <npc id="22176" count="1" respawn="90" pos="-16381 -48650 -10918 16384" />	
        <npc id="22176" count="1" respawn="90" pos="-16291 -48650 -10918 16384" />	
        <npc id="22176" count="1" respawn="90" pos="-16473 -48650 -10918 16384" />	
        <npc id="22176" count="1" respawn="90" pos="-16381 -48391 -10918 16384" />	
        <npc id="22176" count="1" respawn="90" pos="-16291 -48391 -10918 16384" />	
        <npc id="22176" count="1" respawn="90" pos="-16473 -48391 -10918 16384" />	
    </spawn>
    <spawn spawn_bydefault="true"  name="[rune14_mb1916_11]" event_name="[guard_of_andreas]">
        <npc id="22191" count="1" respawn="90" pos="-16385 -53268 -10439 15992" />	
        <npc id="22192" count="1" respawn="90" pos="-16385 -53268 -10439 15992" />	
        <npc id="22193" count="1" respawn="90" pos="-16385 -53268 -10439 15992" />	
    </spawn>
    <spawn spawn_bydefault="true"  name="[rune14_mb1916_12]" event_name="[guard_of_andreas]">
        <territory>	
            <location x="-18174" y="-54844" minz="-10643" maxz="-10243" />
            <location x="-14609" y="-54852" minz="-10643" maxz="-10243" />
            <location x="-14607" y="-52895" minz="-10643" maxz="-10243" />
            <location x="-15352" y="-52161" minz="-10643" maxz="-10243" />
            <location x="-15789" y="-52182" minz="-10643" maxz="-10243" />
            <location x="-16037" y="-51748" minz="-10643" maxz="-10243" />
            <location x="-16395" y="-51630" minz="-10643" maxz="-10243" />
            <location x="-16768" y="-51760" minz="-10643" maxz="-10243" />
            <location x="-17002" y="-52184" minz="-10643" maxz="-10243" />
            <location x="-17437" y="-52184" minz="-10643" maxz="-10243" />
            <location x="-18186" y="-52902" minz="-10643" maxz="-10243" />
        </territory>
        <npc id="22191" count="1" respawn="90" pos="-17150 -54046 -10439 15992" />	
        <npc id="22192" count="1" respawn="90" pos="-17150 -54046 -10439 15992" />	
        <npc id="22193" count="1" respawn="90" />	
    </spawn>
    <spawn spawn_bydefault="true"  name="[rune14_mb1916_13]" event_name="[guard_of_andreas]">
        <npc id="22191" count="1" respawn="90" pos="-15690 -54030 -10439 15992" />	
        <npc id="22192" count="1" respawn="90" pos="-15690 -54030 -10439 15992" />	
        <npc id="22193" count="1" respawn="90" pos="-15690 -54030 -10439 15992" />	
    </spawn>
    <spawn spawn_bydefault="true"  name="[rune14_mb1916_11]" event_name="[guard_of_andreas]">
        <npc id="22191" count="1" respawn="90" pos="-16385 -53268 -10439 15992" />	
        <npc id="22192" count="1" respawn="90" pos="-16385 -53268 -10439 15992" />	
        <npc id="22193" count="1" respawn="90" pos="-16385 -53268 -10439 15992" />	
    </spawn>
    <spawn spawn_bydefault="true"  name="[rune14_mb1916_12]" event_name="[guard_of_andreas]">
        <territory>	
            <location x="-18174" y="-54844" minz="-10643" maxz="-10243" />
            <location x="-14609" y="-54852" minz="-10643" maxz="-10243" />
            <location x="-14607" y="-52895" minz="-10643" maxz="-10243" />
            <location x="-15352" y="-52161" minz="-10643" maxz="-10243" />
            <location x="-15789" y="-52182" minz="-10643" maxz="-10243" />
            <location x="-16037" y="-51748" minz="-10643" maxz="-10243" />
            <location x="-16395" y="-51630" minz="-10643" maxz="-10243" />
            <location x="-16768" y="-51760" minz="-10643" maxz="-10243" />
            <location x="-17002" y="-52184" minz="-10643" maxz="-10243" />
            <location x="-17437" y="-52184" minz="-10643" maxz="-10243" />
            <location x="-18186" y="-52902" minz="-10643" maxz="-10243" />
        </territory>
        <npc id="22191" count="1" respawn="90" pos="-17150 -54046 -10439 15992" />	
        <npc id="22192" count="1" respawn="90" pos="-17150 -54046 -10439 15992" />	
        <npc id="22193" count="1" respawn="90" />	
    </spawn>
    <spawn spawn_bydefault="true"  name="[rune14_mb1916_13]" event_name="[guard_of_andreas]">
        <npc id="22191" count="1" respawn="90" pos="-15690 -54030 -10439 15992" />	
        <npc id="22192" count="1" respawn="90" pos="-15690 -54030 -10439 15992" />	
        <npc id="22193" count="1" respawn="90" pos="-15690 -54030 -10439 15992" />	
    </spawn>
</list>